{
  "source": "500-xml",
  "updatedAt": "2026-06-29 16:43:59",
  "latestIssue": "26073",
  "latestAnnouncement": {
    "issue": "26073",
    "jackpotAmount": 328183968,
    "firstPrizeCount": 10,
    "firstPrizeAmount": 6111492,
    "secondPrizeCount": 136,
    "secondPrizeAmount": 326909,
    "salesAmount": 398594042,
    "drawDate": "2026-06-28"
  },
  "latestDraw": {
    "issue": "26073",
    "drawDate": "2026-06-28 21:15:00",
    "redBalls": [
      9,
      10,
      13,
      16,
      19,
      21
    ],
    "blueBall": 8
  }
}