{
  "source": "500-xml",
  "updatedAt": "2026-07-17 14:56:48",
  "latestIssue": "26081",
  "latestAnnouncement": {
    "issue": "26081",
    "jackpotAmount": 401606257,
    "firstPrizeCount": 5,
    "firstPrizeAmount": 8082773,
    "secondPrizeCount": 137,
    "secondPrizeAmount": 140637,
    "salesAmount": 350765488,
    "drawDate": "2026-07-16"
  },
  "latestDraw": {
    "issue": "26081",
    "drawDate": "2026-07-16 21:15:00",
    "redBalls": [
      6,
      10,
      12,
      15,
      24,
      27
    ],
    "blueBall": 12
  }
}